LHM_Parser/LHM_Parser.py
LHM_Parser/__init__.py
lhm_parser-0.0.1.dist-info/METADATA
lhm_parser-0.0.1.dist-info/WHEEL
lhm_parser-0.0.1.dist-info/licenses/LICENSE
lhm_parser-0.0.1.dist-info/RECORD
